setup.py
gcjio/__init__.py
gcjio.egg-info/PKG-INFO
gcjio.egg-info/SOURCES.txt
gcjio.egg-info/dependency_links.txt
gcjio.egg-info/top_level.txt