Metadata-Version: 1.0
Name: gcjio
Version: 1.7
Summary: Input parser & output formatter for Google Code Jam problems
Home-page: UNKNOWN
Author: Kye W. Shi
Author-email: shi.kye@gmail.com
License: UNKNOWN
Platform: UNKNOWN
